pybls/__init__.py
pybls/cli.py
pybls/pybls.py
pybls/client/__init__.py
pybls/client/bls.py
pybls/client/config.py
pybls/client/response.py
pybls-0.1.0.dist-info/AUTHORS.rst
pybls-0.1.0.dist-info/LICENSE
pybls-0.1.0.dist-info/METADATA
pybls-0.1.0.dist-info/WHEEL
pybls-0.1.0.dist-info/entry_points.txt
pybls-0.1.0.dist-info/top_level.txt
pybls-0.1.0.dist-info/RECORD
